{"structure_type":"collector.role","info":{"question":[{"std":[{"value":"Mike must go home.","ai":"Mike must go home.","audio":""},{"value":"He must go home after school at once.","ai":"He must go home after school at once.","audio":""},{"value":"Mike must go home after school.","ai":"Mike must go home after school.","audio":""},{"value":"Mike must go home after school at once.","ai":"Mike must go home after school at once.","audio":""},{"value":"Mike has to go home after school.","ai":"Mike has to go home after school.","audio":""},{"value":"Mike has to go home after school at once.","ai":"Mike has to go home after school at once.","audio":""},{"value":"Mike has to go home.","ai":"Mike has to go home.","audio":""},{"value":"He must go home after school.","ai":"He must go home after school.","audio":""},{"value":"He must go home.","ai":"He must go home.","audio":""},{"value":"He has to go home after school.","ai":"He has to go home after school.","audio":""},{"value":"He has to go home after school at once.","ai":"He has to go home after school at once.","audio":""},{"value":"He has to go home.","ai":"He has to go home.","audio":""},{"value":"He has to go back home after school.","ai":"He has to go back home after school.","audio":""},{"value":"He has to go back home.","ai":"He has to go back home.","audio":""},{"value":"He must go back home after school.","ai":"He must go back home after school.","audio":""},{"value":"He must go back home after school at once.","ai":"He must go back home after school at once.","audio":""},{"value":"He must go back home.","ai":"He must go back home.","audio":""},{"value":"He has to go back home after school at once.","ai":"He has to go back home after school at once.","audio":""},{"value":"Mike must go back home after school.","ai":"Mike must go back home after school.","audio":""},{"value":"Mike must go back home after school at once.","ai":"Mike must go back home after school at once.","audio":""},{"value":"Mike has to go back home after school.","ai":"Mike has to go back home after school.","audio":""},{"value":"Mike has to go back home after school at once.","ai":"Mike has to go back home after school at once.","audio":""},{"value":"Mike has to go back home.","ai":"Mike has to go back home.","audio":""},{"value":"Mike must go back home.","ai":"Mike must go back home.","audio":""},{"value":"Mike needs to go home after school.","ai":"Mike needs to go home after school.","audio":""},{"value":"Mike needs to go home after school at once.","ai":"Mike needs to go home after school at once.","audio":""},{"value":"Mike needs to go home.","ai":"Mike needs to go home.","audio":""},{"value":"He needs to go home after school.","ai":"He needs to go home after school.","audio":""},{"value":"He needs to go home after school at once.","ai":"He needs to go home after school at once.","audio":""},{"value":"He needs to go home.","ai":"He needs to go home.","audio":""},{"value":"He needs to go back home after school.","ai":"He needs to go back home after school.","audio":""},{"value":"He needs to go back home.","ai":"He needs to go back home.","audio":""},{"value":"He needs to go back home after school at once.","ai":"He needs to go back home after school at once.","audio":""},{"value":"Mike needs to go back home after school.","ai":"Mike needs to go back home after school.","audio":""},{"value":"Mike needs to go back home after school at once.","ai":"Mike needs to go back home after school at once.","audio":""},{"value":"Mike needs to go back home.","ai":"Mike needs to go back home.","audio":""},{"value":"Mike must return home.","ai":"Mike must return home.","audio":""},{"value":"He must return home after school at once.","ai":"He must return home after school at once.","audio":""},{"value":"Mike must return home after school.","ai":"Mike must return home after school.","audio":""},{"value":"Mike must return home after school at once.","ai":"Mike must return home after school at once.","audio":""},{"value":"Mike has to return home after school.","ai":"Mike has to return home after school.","audio":""},{"value":"Mike has to return home after school at once.","ai":"Mike has to return home after school at once.","audio":""},{"value":"Mike has to return home.","ai":"Mike has to return home.","audio":""},{"value":"He must return home after school.","ai":"He must return home after school.","audio":""},{"value":"He must return home.","ai":"He must return home.","audio":""},{"value":"He has to return home after school.","ai":"He has to return home after school.","audio":""},{"value":"He has to return home after school at once.","ai":"He has to return home after school at once.","audio":""},{"value":"He has to return home.","ai":"He has to return home.","audio":""},{"value":"Mike needs to return home after school.","ai":"Mike needs to return home after school.","audio":""},{"value":"Mike needs to return home after school at once.","ai":"Mike needs to return home after school at once.","audio":""},{"value":"Mike needs to return home.","ai":"Mike needs to return home.","audio":""},{"value":"He needs to return home after school.","ai":"He needs to return home after school.","audio":""},{"value":"He needs to return home after school at once.","ai":"He needs to return home after school at once.","audio":""},{"value":"He needs to return home.","ai":"He needs to return home.","audio":""},{"value":"He must go home after school immediately.","ai":"He must go home after school immediately.","audio":""},{"value":"Mike must go home after school immediately.","ai":"Mike must go home after school immediately.","audio":""},{"value":"Mike has to go home after school immediately.","ai":"Mike has to go home after school immediately.","audio":""},{"value":"He has to go home after school immediately.","ai":"He has to go home after school immediately.","audio":""},{"value":"He must go back home after school immediately.","ai":"He must go back home after school immediately.","audio":""},{"value":"He has to go back home after school immediately.","ai":"He has to go back home after school immediately.","audio":""},{"value":"Mike must go back home after school immediately.","ai":"Mike must go back home after school immediately.","audio":""},{"value":"Mike has to go back home after school immediately.","ai":"Mike has to go back home after school immediately.","audio":""},{"value":"Mike needs to go home after school immediately.","ai":"Mike needs to go home after school immediately.","audio":""},{"value":"He needs to go home after school immediately.","ai":"He needs to go home after school immediately.","audio":""},{"value":"He needs to go back home after school immediately.","ai":"He needs to go back home after school immediately.","audio":""},{"value":"Mike needs to go back home after school immediately.","ai":"Mike needs to go back home after school immediately.","audio":""},{"value":"He must return home after school immediately.","ai":"He must return home after school immediately.","audio":""},{"value":"Mike must return home after school immediately.","ai":"Mike must return home after school immediately.","audio":""},{"value":"Mike has to return home after school immediately.","ai":"Mike has to return home after school immediately.","audio":""},{"value":"He has to return home after school immediately.","ai":"He has to return home after school immediately.","audio":""},{"value":"Mike needs to return home after school immediately.","ai":"Mike needs to return home after school immediately.","audio":""},{"value":"He needs to return home after school immediately.","ai":"He needs to return home after school immediately.","audio":""},{"value":"Return home.","ai":"Return home.","audio":""},{"value":"Go home.","ai":"Go home.","audio":""},{"value":"Go back home.","ai":"Go back home.","audio":""}],"ref":[],"ask":"7. What must Mike do after school?","answer":"","askaudio":"ques1askaudio.mp3","aswaudio":"","xh":"1","analyze":"","sucai":"ques1askaudio.mp3","keywords":"Go home | return home","role":"b"},{"std":[{"value":"Before 10 pm.","ai":"Before 10 pm.","audio":""},{"value":"He has to go to bed before 10 pm on school nights.","ai":"He has to go to bed before 10 pm on school nights.","audio":""},{"value":"Mike has to go to bed before 10 pm.","ai":"Mike has to go to bed before 10 pm.","audio":""},{"value":"Mike has to go to bed before 10 pm on school nights.","ai":"Mike has to go to bed before 10 pm on school nights.","audio":""},{"value":"He has to go to sleep before 10 at night.","ai":"He has to go to sleep before 10 at night.","audio":""},{"value":"Mike has to go to bed before 10 on school nights.","ai":"Mike has to go to bed before 10 on school nights.","audio":""},{"value":"Mike has to go to bed before 10.","ai":"Mike has to go to bed before 10.","audio":""},{"value":"Mike has to go to bed before 10 in the evening on school nights.","ai":"Mike has to go to bed before 10 in the evening on school nights.","audio":""},{"value":"Mike has to go to bed before 10 in the evening.","ai":"Mike has to go to bed before 10 in the evening.","audio":""},{"value":"Mike has to go to bed before 10 at night on school nights.","ai":"Mike has to go to bed before 10 at night on school nights.","audio":""},{"value":"Mike has to go to bed before 10 at night.","ai":"Mike has to go to bed before 10 at night.","audio":""},{"value":"Mike has to go to sleep before 10 pm on school nights.","ai":"Mike has to go to sleep before 10 pm on school nights.","audio":""},{"value":"Mike has to go to sleep before 10 pm.","ai":"Mike has to go to sleep before 10 pm.","audio":""},{"value":"Mike has to go to sleep before 10 on school nights.","ai":"Mike has to go to sleep before 10 on school nights.","audio":""},{"value":"Mike has to go to sleep before 10.","ai":"Mike has to go to sleep before 10.","audio":""},{"value":"Mike has to go to sleep before 10 in the evening on school nights.","ai":"Mike has to go to sleep before 10 in the evening on school nights.","audio":""},{"value":"Mike has to go to sleep before 10 in the evening.","ai":"Mike has to go to sleep before 10 in the evening.","audio":""},{"value":"Mike has to go to sleep before 10 at night on school nights.","ai":"Mike has to go to sleep before 10 at night on school nights.","audio":""},{"value":"Mike has to go to sleep before 10 at night.","ai":"Mike has to go to sleep before 10 at night.","audio":""},{"value":"Mike needs go to bed before 10 pm on school nights.","ai":"Mike needs go to bed before 10 pm on school nights.","audio":""},{"value":"Mike needs go to bed before 10 pm.","ai":"Mike needs go to bed before 10 pm.","audio":""},{"value":"Mike needs go to bed before 10 on school nights.","ai":"Mike needs go to bed before 10 on school nights.","audio":""},{"value":"Mike needs go to bed before 10.","ai":"Mike needs go to bed before 10.","audio":""},{"value":"Mike needs go to bed before 10 in the evening on school nights.","ai":"Mike needs go to bed before 10 in the evening on school nights.","audio":""},{"value":"Mike needs go to bed before 10 in the evening.","ai":"Mike needs go to bed before 10 in the evening.","audio":""},{"value":"Mike needs go to bed before 10 at night on school nights.","ai":"Mike needs go to bed before 10 at night on school nights.","audio":""},{"value":"Mike needs go to bed before 10 at night.","ai":"Mike needs go to bed before 10 at night.","audio":""},{"value":"Mike needs go to sleep before 10 pm on school nights.","ai":"Mike needs go to sleep before 10 pm on school nights.","audio":""},{"value":"Mike needs go to sleep before 10 pm.","ai":"Mike needs go to sleep before 10 pm.","audio":""},{"value":"Mike needs go to sleep before 10 on school nights.","ai":"Mike needs go to sleep before 10 on school nights.","audio":""},{"value":"Mike needs go to sleep before 10.","ai":"Mike needs go to sleep before 10.","audio":""},{"value":"Mike needs go to sleep before 10 in the evening on school nights.","ai":"Mike needs go to sleep before 10 in the evening on school nights.","audio":""},{"value":"Mike needs go to sleep before 10 in the evening.","ai":"Mike needs go to sleep before 10 in the evening.","audio":""},{"value":"Mike must go to bed before 10 in the evening on school nights.","ai":"Mike must go to bed before 10 in the evening on school nights.","audio":""},{"value":"Mike needs go to sleep before 10 at night on school nights.","ai":"Mike needs go to sleep before 10 at night on school nights.","audio":""},{"value":"Mike needs go to sleep before 10 at night.","ai":"Mike needs go to sleep before 10 at night.","audio":""},{"value":"Mike must go to bed before 10 pm on school nights.","ai":"Mike must go to bed before 10 pm on school nights.","audio":""},{"value":"Mike must go to bed before 10 pm.","ai":"Mike must go to bed before 10 pm.","audio":""},{"value":"Mike must go to bed before 10 on school nights.","ai":"Mike must go to bed before 10 on school nights.","audio":""},{"value":"Mike must go to bed before 10.","ai":"Mike must go to bed before 10.","audio":""},{"value":"Mike must go to bed before 10 in the evening.","ai":"Mike must go to bed before 10 in the evening.","audio":""},{"value":"Mike must go to bed before 10 at night on school nights.","ai":"Mike must go to bed before 10 at night on school nights.","audio":""},{"value":"Mike must go to bed before 10 at night.","ai":"Mike must go to bed before 10 at night.","audio":""},{"value":"Mike must go to sleep before 10 pm on school nights.","ai":"Mike must go to sleep before 10 pm on school nights.","audio":""},{"value":"Mike must go to sleep before 10 pm.","ai":"Mike must go to sleep before 10 pm.","audio":""},{"value":"Mike must go to sleep before 10 on school nights.","ai":"Mike must go to sleep before 10 on school nights.","audio":""},{"value":"Mike must go to sleep before 10.","ai":"Mike must go to sleep before 10.","audio":""},{"value":"Mike must go to sleep before 10 in the evening on school nights.","ai":"Mike must go to sleep before 10 in the evening on school nights.","audio":""},{"value":"Mike must go to sleep before 10 in the evening.","ai":"Mike must go to sleep before 10 in the evening.","audio":""},{"value":"Mike must go to sleep before 10 at night on school nights.","ai":"Mike must go to sleep before 10 at night on school nights.","audio":""},{"value":"Mike must go to sleep before 10 at night.","ai":"Mike must go to sleep before 10 at night.","audio":""},{"value":"He has to go to bed before 10 pm.","ai":"He has to go to bed before 10 pm.","audio":""},{"value":"He has to go to bed before 10 on school nights.","ai":"He has to go to bed before 10 on school nights.","audio":""},{"value":"He has to go to bed before 10.","ai":"He has to go to bed before 10.","audio":""},{"value":"He has to go to bed before 10 in the evening on school nights.","ai":"He has to go to bed before 10 in the evening on school nights.","audio":""},{"value":"He has to go to bed before 10 in the evening.","ai":"He has to go to bed before 10 in the evening.","audio":""},{"value":"He has to go to bed before 10 at night on school nights.","ai":"He has to go to bed before 10 at night on school nights.","audio":""},{"value":"He has to go to bed before 10 at night.","ai":"He has to go to bed before 10 at night.","audio":""},{"value":"He has to go to sleep before 10 pm on school nights.","ai":"He has to go to sleep before 10 pm on school nights.","audio":""},{"value":"He has to go to sleep before 10 pm.","ai":"He has to go to sleep before 10 pm.","audio":""},{"value":"He has to go to sleep before 10 on school nights.","ai":"He has to go to sleep before 10 on school nights.","audio":""},{"value":"He has to go to sleep before 10.","ai":"He has to go to sleep before 10.","audio":""},{"value":"He has to go to sleep before 10 in the evening on school nights.","ai":"He has to go to sleep before 10 in the evening on school nights.","audio":""},{"value":"He has to go to sleep before 10 in the evening.","ai":"He has to go to sleep before 10 in the evening.","audio":""},{"value":"He has to go to sleep before 10 at night on school nights.","ai":"He has to go to sleep before 10 at night on school nights.","audio":""},{"value":"He needs go to bed before 10 pm on school nights.","ai":"He needs go to bed before 10 pm on school nights.","audio":""},{"value":"He needs go to bed before 10 pm.","ai":"He needs go to bed before 10 pm.","audio":""},{"value":"He needs go to bed before 10 on school nights.","ai":"He needs go to bed before 10 on school nights.","audio":""},{"value":"He needs go to bed before 10.","ai":"He needs go to bed before 10.","audio":""},{"value":"He needs go to sleep before 10.","ai":"He needs go to sleep before 10.","audio":""},{"value":"He needs go to bed before 10 in the evening on school nights.","ai":"He needs go to bed before 10 in the evening on school nights.","audio":""},{"value":"He needs go to bed before 10 in the evening.","ai":"He needs go to bed before 10 in the evening.","audio":""},{"value":"He needs go to bed before 10 at night on school nights.","ai":"He needs go to bed before 10 at night on school nights.","audio":""},{"value":"He needs go to bed before 10 at night.","ai":"He needs go to bed before 10 at night.","audio":""},{"value":"He needs go to sleep before 10 pm on school nights.","ai":"He needs go to sleep before 10 pm on school nights.","audio":""},{"value":"He needs go to sleep before 10 pm.","ai":"He needs go to sleep before 10 pm.","audio":""},{"value":"He needs go to sleep before 10 on school nights.","ai":"He needs go to sleep before 10 on school nights.","audio":""},{"value":"He needs go to sleep before 10 in the evening on school nights.","ai":"He needs go to sleep before 10 in the evening on school nights.","audio":""},{"value":"He needs go to sleep before 10 in the evening.","ai":"He needs go to sleep before 10 in the evening.","audio":""},{"value":"He needs go to sleep before 10 at night on school nights.","ai":"He needs go to sleep before 10 at night on school nights.","audio":""},{"value":"He needs go to sleep before 10 at night.","ai":"He needs go to sleep before 10 at night.","audio":""},{"value":"He must go to bed before 10 pm on school nights.","ai":"He must go to bed before 10 pm on school nights.","audio":""},{"value":"He must go to bed before 10 pm.","ai":"He must go to bed before 10 pm.","audio":""},{"value":"He must go to bed before 10 on school nights.","ai":"He must go to bed before 10 on school nights.","audio":""},{"value":"He must go to bed before 10.","ai":"He must go to bed before 10.","audio":""},{"value":"He must go to bed before 10 in the evening on school nights.","ai":"He must go to bed before 10 in the evening on school nights.","audio":""},{"value":"He must go to bed before 10 in the evening.","ai":"He must go to bed before 10 in the evening.","audio":""},{"value":"He must go to bed before 10 at night on school nights.","ai":"He must go to bed before 10 at night on school nights.","audio":""},{"value":"He must go to bed before 10 at night.","ai":"He must go to bed before 10 at night.","audio":""},{"value":"He must go to sleep before 10 pm on school nights.","ai":"He must go to sleep before 10 pm on school nights.","audio":""},{"value":"He must go to sleep before 10 pm.","ai":"He must go to sleep before 10 pm.","audio":""},{"value":"He must go to sleep before 10 on school nights.","ai":"He must go to sleep before 10 on school nights.","audio":""},{"value":"He must go to sleep before 10.","ai":"He must go to sleep before 10.","audio":""},{"value":"He must go to sleep before 10 in the evening on school nights.","ai":"He must go to sleep before 10 in the evening on school nights.","audio":""},{"value":"He must go to sleep before 10 in the evening.","ai":"He must go to sleep before 10 in the evening.","audio":""},{"value":"He must go to sleep before 10 at night on school nights.","ai":"He must go to sleep before 10 at night on school nights.","audio":""},{"value":"He must go to sleep before 10 at night.","ai":"He must go to sleep before 10 at night.","audio":""},{"value":"On school nights, Mike has to go to bed before 10 pm.","ai":"On school nights, Mike has to go to bed before 10 pm.","audio":""},{"value":"On school nights, he needs go to sleep before 10.","ai":"On school nights, he needs go to sleep before 10.","audio":""},{"value":"On school nights, Mike must go to bed before 10 in the evening.","ai":"On school nights, Mike must go to bed before 10 in the evening.","audio":""},{"value":"On school nights, he has to go to sleep before 10 at night.","ai":"On school nights, he has to go to sleep before 10 at night.","audio":""},{"value":"On school nights, Mike has to go to bed before 10.","ai":"On school nights, Mike has to go to bed before 10.","audio":""},{"value":"On school nights, Mike has to go to bed before 10 in the evening.","ai":"On school nights, Mike has to go to bed before 10 in the evening.","audio":""},{"value":"On school nights, Mike has to go to bed before 10 at night.","ai":"On school nights, Mike has to go to bed before 10 at night.","audio":""},{"value":"On school nights, Mike has to go to sleep before 10 pm.","ai":"On school nights, Mike has to go to sleep before 10 pm.","audio":""},{"value":"On school nights, Mike has to go to sleep before 10.","ai":"On school nights, Mike has to go to sleep before 10.","audio":""},{"value":"On school nights, Mike has to go to sleep before 10 in the evening.","ai":"On school nights, Mike has to go to sleep before 10 in the evening.","audio":""},{"value":"On school nights, Mike has to go to sleep before 10 at night.","ai":"On school nights, Mike has to go to sleep before 10 at night.","audio":""},{"value":"On school nights, Mike needs go to bed before 10 pm.","ai":"On school nights, Mike needs go to bed before 10 pm.","audio":""},{"value":"On school nights, Mike needs go to bed before 10.","ai":"On school nights, Mike needs go to bed before 10.","audio":""},{"value":"On school nights, Mike needs go to bed before 10 in the evening.","ai":"On school nights, Mike needs go to bed before 10 in the evening.","audio":""},{"value":"On school nights, Mike needs go to bed before 10 at night.","ai":"On school nights, Mike needs go to bed before 10 at night.","audio":""},{"value":"On school nights, Mike needs go to sleep before 10 pm.","ai":"On school nights, Mike needs go to sleep before 10 pm.","audio":""},{"value":"On school nights, Mike needs go to sleep before 10.","ai":"On school nights, Mike needs go to sleep before 10.","audio":""},{"value":"On school nights, Mike needs go to sleep before 10 in the evening.","ai":"On school nights, Mike needs go to sleep before 10 in the evening.","audio":""},{"value":"On school nights, Mike needs go to sleep before 10 at night.","ai":"On school nights, Mike needs go to sleep before 10 at night.","audio":""},{"value":"On school nights, Mike must go to bed before 10 pm.","ai":"On school nights, Mike must go to bed before 10 pm.","audio":""},{"value":"On school nights, Mike must go to bed before 10.","ai":"On school nights, Mike must go to bed before 10.","audio":""},{"value":"On school nights, Mike must go to bed before 10 at night.","ai":"On school nights, Mike must go to bed before 10 at night.","audio":""},{"value":"On school nights, Mike must go to sleep before 10 pm.","ai":"On school nights, Mike must go to sleep before 10 pm.","audio":""},{"value":"On school nights, Mike must go to sleep before 10.","ai":"On school nights, Mike must go to sleep before 10.","audio":""},{"value":"On school nights, Mike must go to sleep before 10 in the evening.","ai":"On school nights, Mike must go to sleep before 10 in the evening.","audio":""},{"value":"On school nights, Mike must go to sleep before 10 at night.","ai":"On school nights, Mike must go to sleep before 10 at night.","audio":""},{"value":"On school nights, he has to go to bed before 10 pm.","ai":"On school nights, he has to go to bed before 10 pm.","audio":""},{"value":"On school nights, he has to go to bed before 10.","ai":"On school nights, he has to go to bed before 10.","audio":""},{"value":"On school nights, he has to go to bed before 10 in the evening.","ai":"On school nights, he has to go to bed before 10 in the evening.","audio":""},{"value":"On school nights, he has to go to bed before 10 at night.","ai":"On school nights, he has to go to bed before 10 at night.","audio":""},{"value":"On school nights, he has to go to sleep before 10 pm.","ai":"On school nights, he has to go to sleep before 10 pm.","audio":""},{"value":"On school nights, he has to go to sleep before 10.","ai":"On school nights, he has to go to sleep before 10.","audio":""},{"value":"On school nights, he has to go to sleep before 10 in the evening.","ai":"On school nights, he has to go to sleep before 10 in the evening.","audio":""},{"value":"On school nights, he needs go to bed before 10 pm.","ai":"On school nights, he needs go to bed before 10 pm.","audio":""},{"value":"On school nights, he needs go to bed before 10.","ai":"On school nights, he needs go to bed before 10.","audio":""},{"value":"On school nights, he needs go to bed before 10 in the evening.","ai":"On school nights, he needs go to bed before 10 in the evening.","audio":""},{"value":"On school nights, he needs go to bed before 10 at night.","ai":"On school nights, he needs go to bed before 10 at night.","audio":""},{"value":"On school nights, he needs go to sleep before 10 pm.","ai":"On school nights, he needs go to sleep before 10 pm.","audio":""},{"value":"On school nights, he needs go to sleep before 10 in the evening.","ai":"On school nights, he needs go to sleep before 10 in the evening.","audio":""},{"value":"On school nights, he needs go to sleep before 10 at night.","ai":"On school nights, he needs go to sleep before 10 at night.","audio":""},{"value":"On school nights, he must go to bed before 10 pm.","ai":"On school nights, he must go to bed before 10 pm.","audio":""},{"value":"On school nights, he must go to bed before 10.","ai":"On school nights, he must go to bed before 10.","audio":""},{"value":"On school nights, he must go to bed before 10 in the evening.","ai":"On school nights, he must go to bed before 10 in the evening.","audio":""},{"value":"On school nights, he must go to bed before 10 at night.","ai":"On school nights, he must go to bed before 10 at night.","audio":""},{"value":"On school nights, he must go to sleep before 10 pm.","ai":"On school nights, he must go to sleep before 10 pm.","audio":""},{"value":"On school nights, he must go to sleep before 10.","ai":"On school nights, he must go to sleep before 10.","audio":""},{"value":"On school nights, he must go to sleep before 10 in the evening.","ai":"On school nights, he must go to sleep before 10 in the evening.","audio":""},{"value":"On school nights, he must go to sleep before 10 at night.","ai":"On school nights, he must go to sleep before 10 at night.","audio":""},{"value":"Before 10.","ai":"Before 10.","audio":""},{"value":"Before 10 in the evening.","ai":"Before 10 in the evening.","audio":""},{"value":"Before 10 at night.","ai":"Before 10 at night.","audio":""}],"ref":[],"ask":"8. When does Mike have to go to bed on school nights?","answer":"","askaudio":"ques2askaudio.mp3","aswaudio":"","xh":"2","analyze":"","sucai":"ques2askaudio.mp3","keywords":"Before ten","role":"b"},{"std":[{"value":"Angry.","ai":"Angry.","audio":""},{"value":"Mike's parents will feel angry.","ai":"Mike's parents will feel angry.","audio":""},{"value":"They will get angry if he leaves things around the house.","ai":"They will get angry if he leaves things around the house.","audio":""},{"value":"His parents will get angry.","ai":"His parents will get angry.","audio":""},{"value":"They'll get angry.","ai":"They'll get angry.","audio":""},{"value":"His parents are going to get angry if he leaves things around the house.","ai":"His parents are going to get angry if he leaves things around the house.","audio":""},{"value":"They are going to get angry.","ai":"They are going to get angry.","audio":""},{"value":"They're going to get angry if he leaves things around the house.","ai":"They're going to get angry if he leaves things around the house.","audio":""},{"value":"His parents will get angry if he leaves things around the house.","ai":"His parents will get angry if he leaves things around the house.","audio":""},{"value":"They will get angry.","ai":"They will get angry.","audio":""},{"value":"They'll get angry if he leaves things around the house.","ai":"They'll get angry if he leaves things around the house.","audio":""},{"value":"His parents are going to get angry.","ai":"His parents are going to get angry.","audio":""},{"value":"They are going to get angry if he leaves things around the house.","ai":"They are going to get angry if he leaves things around the house.","audio":""},{"value":"They're going to get angry.","ai":"They're going to get angry.","audio":""},{"value":"Mike's parents will get angry.","ai":"Mike's parents will get angry.","audio":""},{"value":"Mike's parents are going to get angry if he leaves things around the house.","ai":"Mike's parents are going to get angry if he leaves things around the house.","audio":""},{"value":"Mike's parents will get angry if he leaves things around the house.","ai":"Mike's parents will get angry if he leaves things around the house.","audio":""},{"value":"Mike's parents are going to get angry.His parents will feel angry.","ai":"Mike's parents are going to get angry.His parents will feel angry.","audio":""},{"value":"They will feel angry if he leaves things around the house.","ai":"They will feel angry if he leaves things around the house.","audio":""},{"value":"They'll feel angry.","ai":"They'll feel angry.","audio":""},{"value":"His parents are going to feel angry if he leaves things around the house.","ai":"His parents are going to feel angry if he leaves things around the house.","audio":""},{"value":"They are going to feel angry.","ai":"They are going to feel angry.","audio":""},{"value":"They're going to feel angry if he leaves things around the house.","ai":"They're going to feel angry if he leaves things around the house.","audio":""},{"value":"His parents will feel angry if he leaves things around the house.","ai":"His parents will feel angry if he leaves things around the house.","audio":""},{"value":"They will feel angry.","ai":"They will feel angry.","audio":""},{"value":"They'll feel angry if he leaves things around the house.","ai":"They'll feel angry if he leaves things around the house.","audio":""},{"value":"His parents are going to feel angry.","ai":"His parents are going to feel angry.","audio":""},{"value":"They are going to feel angry if he leaves things around the house.","ai":"They are going to feel angry if he leaves things around the house.","audio":""},{"value":"They're going to feel angry.","ai":"They're going to feel angry.","audio":""},{"value":"Mike's parents are going to feel angry if he leaves things around the house.","ai":"Mike's parents are going to feel angry if he leaves things around the house.","audio":""},{"value":"Mike's parents will feel angry if he leaves things around the house.","ai":"Mike's parents will feel angry if he leaves things around the house.","audio":""},{"value":"Mike's parents are going to feel angry.","ai":"Mike's parents are going to feel angry.","audio":""},{"value":"If he leaves things around the house, his parents will feel angry.","ai":"If he leaves things around the house, his parents will feel angry.","audio":""},{"value":"If he leaves things around the house, his parents will get angry.","ai":"If he leaves things around the house, his parents will get angry.","audio":""},{"value":"If Mike leaves things around the house, his parents will feel angry.","ai":"If Mike leaves things around the house, his parents will feel angry.","audio":""},{"value":"If Mike leaves things around the house, his parents will get angry.","ai":"If Mike leaves things around the house, his parents will get angry.","audio":""},{"value":"If he leaves things around the house, they will feel angry.","ai":"If he leaves things around the house, they will feel angry.","audio":""},{"value":"If he leaves things around the house, they will get angry.","ai":"If he leaves things around the house, they will get angry.","audio":""},{"value":"If Mike leaves things around the house, they will feel angry.","ai":"If Mike leaves things around the house, they will feel angry.","audio":""},{"value":"If Mike leaves things around the house, they will get angry.","ai":"If Mike leaves things around the house, they will get angry.","audio":""},{"value":"Mad.","ai":"Mad.","audio":""},{"value":"Mike's parents will feel mad.","ai":"Mike's parents will feel mad.","audio":""},{"value":"They will get mad if he leaves things around the house.","ai":"They will get mad if he leaves things around the house.","audio":""},{"value":"His parents will get mad.","ai":"His parents will get mad.","audio":""},{"value":"They'll get mad.","ai":"They'll get mad.","audio":""},{"value":"His parents are going to get mad if he leaves things around the house.","ai":"His parents are going to get mad if he leaves things around the house.","audio":""},{"value":"They are going to get mad.","ai":"They are going to get mad.","audio":""},{"value":"They're going to get mad if he leaves things around the house.","ai":"They're going to get mad if he leaves things around the house.","audio":""},{"value":"His parents will get mad if he leaves things around the house.","ai":"His parents will get mad if he leaves things around the house.","audio":""},{"value":"They will get mad.","ai":"They will get mad.","audio":""},{"value":"They'll get mad if he leaves things around the house.","ai":"They'll get mad if he leaves things around the house.","audio":""},{"value":"His parents are going to get mad.","ai":"His parents are going to get mad.","audio":""},{"value":"They are going to get mad if he leaves things around the house.","ai":"They are going to get mad if he leaves things around the house.","audio":""},{"value":"They're going to get mad.","ai":"They're going to get mad.","audio":""},{"value":"Mike's parents will get mad.","ai":"Mike's parents will get mad.","audio":""},{"value":"Mike's parents are going to get mad if he leaves things around the house.","ai":"Mike's parents are going to get mad if he leaves things around the house.","audio":""},{"value":"Mike's parents will get mad if he leaves things around the house.","ai":"Mike's parents will get mad if he leaves things around the house.","audio":""},{"value":"Mike's parents are going to get mad.His parents will feel mad.","ai":"Mike's parents are going to get mad.His parents will feel mad.","audio":""},{"value":"They will feel mad if he leaves things around the house.","ai":"They will feel mad if he leaves things around the house.","audio":""},{"value":"They'll feel mad.","ai":"They'll feel mad.","audio":""},{"value":"His parents are going to feel mad if he leaves things around the house.","ai":"His parents are going to feel mad if he leaves things around the house.","audio":""},{"value":"They are going to feel mad.","ai":"They are going to feel mad.","audio":""},{"value":"They're going to feel mad if he leaves things around the house.","ai":"They're going to feel mad if he leaves things around the house.","audio":""},{"value":"His parents will feel mad if he leaves things around the house.","ai":"His parents will feel mad if he leaves things around the house.","audio":""},{"value":"They will feel mad.","ai":"They will feel mad.","audio":""},{"value":"They'll feel mad if he leaves things around the house.","ai":"They'll feel mad if he leaves things around the house.","audio":""},{"value":"His parents are going to feel mad.","ai":"His parents are going to feel mad.","audio":""},{"value":"They are going to feel mad if he leaves things around the house.","ai":"They are going to feel mad if he leaves things around the house.","audio":""},{"value":"They're going to feel mad.","ai":"They're going to feel mad.","audio":""},{"value":"Mike's parents are going to feel mad if he leaves things around the house.","ai":"Mike's parents are going to feel mad if he leaves things around the house.","audio":""},{"value":"Mike's parents will feel mad if he leaves things around the house.","ai":"Mike's parents will feel mad if he leaves things around the house.","audio":""},{"value":"Mike's parents are going to feel mad.","ai":"Mike's parents are going to feel mad.","audio":""},{"value":"If he leaves things around the house, his parents will feel mad.","ai":"If he leaves things around the house, his parents will feel mad.","audio":""},{"value":"If he leaves things around the house, his parents will get mad.","ai":"If he leaves things around the house, his parents will get mad.","audio":""},{"value":"If Mike leaves things around the house, his parents will feel mad.","ai":"If Mike leaves things around the house, his parents will feel mad.","audio":""},{"value":"If Mike leaves things around the house, his parents will get mad.","ai":"If Mike leaves things around the house, his parents will get mad.","audio":""},{"value":"If he leaves things around the house, they will feel mad.","ai":"If he leaves things around the house, they will feel mad.","audio":""},{"value":"If he leaves things around the house, they will get mad.","ai":"If he leaves things around the house, they will get mad.","audio":""},{"value":"If Mike leaves things around the house, they will feel mad.","ai":"If Mike leaves things around the house, they will feel mad.","audio":""},{"value":"If Mike leaves things around the house, they will get mad.","ai":"If Mike leaves things around the house, they will get mad.","audio":""}],"ref":[],"ask":"9. How will Mike's parents feel if he leaves things around the house?","answer":"","askaudio":"ques3askaudio.mp3","aswaudio":"","xh":"3","analyze":"","sucai":"ques3askaudio.mp3","keywords":"Angry | mad","role":"b"},{"std":[{"value":"Mike's friends.","ai":"Mike's friends.","audio":""},{"value":"Mike's friends think the rules are too strict.","ai":"Mike's friends think the rules are too strict.","audio":""},{"value":"Mike's friends think they are too strict.","ai":"Mike's friends think they are too strict.","audio":""},{"value":"Mike's friends think they're too strict.","ai":"Mike's friends think they're too strict.","audio":""},{"value":"They are Mike's friends.","ai":"They are Mike's friends.","audio":""},{"value":"They're Mike's friends.","ai":"They're Mike's friends.","audio":""},{"value":"Mike's friends do.","ai":"Mike's friends do.","audio":""},{"value":"Mike's friends think so.","ai":"Mike's friends think so.","audio":""},{"value":"Mike's friends believe the rules are very strict.","ai":"Mike's friends believe the rules are very strict.","audio":""},{"value":"Mike's friends believe they are very strict.","ai":"Mike's friends believe they are very strict.","audio":""}],"ref":[],"ask":"10. Who thinks the rules are too strict?","answer":"","askaudio":"ques4askaudio.mp3","aswaudio":"","xh":"4","analyze":"","sucai":"ques4askaudio.mp3","keywords":"Mike's friends","role":"b"}],"image":"","video":"","value":"<p>I'm Mike. My parents are strict with me. They have made some family rules for me. The first rule is to study hard at school. Besides, I must go home after school at once. I have to go to bed before 10 pm on school nights. But during the holidays, I can stay up late. Moreover, I have to clean my room. My parents will get angry if I leave things around the house. I should keep my room tidy. My friends think the rules are too strict. But I'm proud of myself because I've developed good habits because of the rules.<\/p>","stid":"492088","audio":"content.mp3"}}